{
  "respondent": "MARY KATE FERGUSON, PA-C",
  "license_number": "C01577",
  "date": "2019-04-11",
  "summary": "Mary Kate Ferguson, PA-C, violated a prior Disposition Agreement multiple times by failing to comply with her Maryland Professional Rehabilitation Program (MPRP) Participant Rehabilitation Agreement, initially entered into after two DUI convictions. As a result, her physician assistant license is suspended for a minimum of six months, followed by five years of probation, both requiring continued compliance with MPRP.",
  "keywords": [
    "physician assistant",
    "suspension",
    "probation",
    "rehabilitation program",
    "DUI"
  ]
}