{
  "respondent": "BERNARD COHEN, M.D.",
  "license_number": "D26518",
  "date": "2023-03-22",
  "summary": "Bernard Cohen, M.D., had his medical license suspended in July 2022 due to professional, physical, or mental incompetence stemming from a medical condition precluding safe practice. He subsequently petitioned to terminate this suspension, but after reviewing multiple evaluations, the Board denied his petition. Consequently, Dr. Cohen's medical license remains suspended, as he is deemed unsafe to return to clinical practice.",
  "keywords": [
    "Physician",
    "License suspension",
    "Incompetence",
    "Medical condition",
    "Disciplinary action"
  ]
}