{
  "respondent": "WILLIAM S. VAUGHN, III, M.D.",
  "license_number": "D43641",
  "date": "2017-11-29",
  "summary": "Dr. William S. Vaughn, III's medical license was summarily suspended by the Maryland State Board of Physicians due to allegations of unlawfully prescribing controlled dangerous substances, specifically 66 counts of Adderall prescriptions outside of professional practice. He was also found to have continued prescribing after surrendering his DEA registration and practiced medicine with an expired license, leading to emergency action by the Board.",
  "keywords": [
    "physician",
    "summary suspension",
    "controlled substances",
    "unlawful prescribing",
    "expired license"
  ]
}