{
  "respondent": "SAMUEL RAJARATNAM, M.D.",
  "license_number": "D76564",
  "date": "2017-10-09",
  "summary": "Samuel Rajaratnam, M.D., had his medical license summarily suspended after being found professionally, physically, or mentally incompetent. The Board's investigation, prompted by a complaint that he recommended a patient share Seroquel with her minor son, led to a neuropsychological evaluation recommending he cease practicing medicine. He is ordered to enroll in the Maryland Professional Rehabilitation Program, with conditions for potential reinstatement of his license.",
  "keywords": [
    "Physician",
    "License suspension",
    "Professional incompetence",
    "Medication recommendation",
    "Rehabilitation program"
  ]
}