{
  "respondent": "ANDREW S. CRUZ, M.D.",
  "license_number": "D95396",
  "date": "2023-10-24",
  "summary": "Andrew S. Cruz, M.D., was disciplined by the Arizona Medical Board, which led to the suspension of his Maryland medical license by a Consent Agreement on October 24, 2023. The suspension of his Maryland license has since been terminated, as his ability to practice medicine in Arizona was restored.",
  "keywords": [
    "Physician",
    "License suspension",
    "Disciplinary action",
    "Interstate reciprocity",
    "License restoration"
  ]
}