{
  "respondent": "Melissa Rutherford, RCP",
  "license_number": "L07049",
  "date": "2021-04-15",
  "summary": "Disciplinary Panel A of the Maryland State Board of Physicians summarily suspended Melissa Rutherford's respiratory care license on March 31, 2021. Following a post-deprivation hearing on April 14, 2021, the Panel reaffirmed the suspension, finding that public health, safety, or welfare imperatively required it. Her license to practice respiratory care remains summarily suspended.",
  "keywords": [
    "Respiratory Care",
    "License Suspension",
    "Summary Suspension",
    "Disciplinary Action",
    "Maryland"
  ]
}