{
  "respondent": "Fysal Henson, NMT",
  "license_number": "N01623",
  "date": "2023-06-01",
  "summary": "Fysal Henson, a Nuclear Medicine Technologist, faced disciplinary action for failing to comply with a previous Board order, including repeated non-compliance with the Maryland Professional Rehabilitation Program (MPRP) and practicing while his license was suspended. The Maryland State Board of Physicians reprimanded Mr. Henson and imposed an additional minimum six-month suspension of his nuclear medicine technologist license.",
  "keywords": [
    "Nuclear Medicine Technologist",
    "License Suspension",
    "MPRP non-compliance",
    "Practicing while suspended",
    "Disciplinary Action"
  ]
}